Bot/__init__.py
Bot/bot.py
Bot/cine.py
Bot/codesTemps.py
Bot/config.py
Bot/help.txt
Bot/itinerary.py
Bot/news.py
Bot/opinion.py
Bot/request.py
Bot/resto.py
Bot/weather.py
Bot_Externe-0.0.10.dist-info/LICENSE
Bot_Externe-0.0.10.dist-info/METADATA
Bot_Externe-0.0.10.dist-info/WHEEL
Bot_Externe-0.0.10.dist-info/top_level.txt
Bot_Externe-0.0.10.dist-info/RECORD
