Metadata-Version: 2.1
Name: Bot-Externe
Version: 0.0.10
Summary: ChatBot effectuant des appels sur des API pour obtenir des infos tels que la meteo, des nouvelles, des itinéraires etc..
Home-page: https://github.com/CardinPatson/noyau_devII_2TM2
Author: Groupe-2TM2-2
Author-email: cardin.tiako@gmail.com
License: UNKNOWN
Platform: UNKNOWN
Classifier: Programming Language :: Python :: 3
Classifier: License :: OSI Approved :: GNU General Public License v3 (GPLv3)
Requires-Python: >=3.8
License-File: LICENSE
